README.md
setup.cfg
setup.py
namecheapapi/__init__.py
namecheapapi.egg-info/PKG-INFO
namecheapapi.egg-info/SOURCES.txt
namecheapapi.egg-info/dependency_links.txt
namecheapapi.egg-info/top_level.txt
namecheapapi/api/__init__.py
namecheapapi/api/commands.py
namecheapapi/api/domains.py
namecheapapi/api/exceptions.py
namecheapapi/api/session.py
namecheapapi/tests/domain_tests.py