Metadata-Version: 1.1
Name: namecheapapi
Version: 0.1.1
Summary: Python Namecheap API wrapper
Home-page: https://github.com/yonjuuni/namecheapapi
Author: Alex Sanchez
Author-email: alex@s1ck.org
License: MIT
Keywords: namecheap,domain,dns
Platform: any
Classifier: License :: OSI Approved :: MIT License
Classifier: Intended Audience :: Developers
Classifier: Programming Language :: Python :: 3.5
Classifier: Environment :: Web Environment
Classifier: Development Status :: 3 - Alpha
